pygame-lib/Collision2D.py
pygame-lib/Physics2D.py
pygame-lib/__init__.py
pygame-lib/objectClasses.py
pygameutilities/Collision2D.py
pygameutilities/Physics2D.py
pygameutilities/__init__.py
pygameutilities/objectClasses.py
pygameutils/Collision2D.py
pygameutils/Physics2D.py
pygameutils/__init__.py
pygameutils/objectClasses.py
pygameutilities-1.0.2.dist-info/LICENSE
pygameutilities-1.0.2.dist-info/METADATA
pygameutilities-1.0.2.dist-info/WHEEL
pygameutilities-1.0.2.dist-info/top_level.txt
pygameutilities-1.0.2.dist-info/RECORD
