Metadata-Version: 2.1
Name: pygameutilities
Version: 1.0.2
Summary: A small pygame library to make your life easier
Author: Emilio Mendoza
Author-email: Ironislife39@gmail.com
Keywords: python,pygame,physics
Classifier: Development Status :: 1 - Planning
Classifier: Intended Audience :: Developers
Classifier: Programming Language :: Python :: 3
Classifier: Operating System :: Unix
Classifier: Operating System :: MacOS :: MacOS X
Classifier: Operating System :: Microsoft :: Windows
License-File: LICENSE
Requires-Dist: pygame
